README.md
setup.py
order_flower_bot/__init__.py
order_flower_bot/bot.py
order_flower_bot/handler.py
pylexbuilder/__init__.py
pylexbuilder/props.py
pylexbuilder/utils.py
pylexbuilder.egg-info/PKG-INFO
pylexbuilder.egg-info/SOURCES.txt
pylexbuilder.egg-info/dependency_links.txt
pylexbuilder.egg-info/requires.txt
pylexbuilder.egg-info/top_level.txt
pylexbuilder.egg-info/zip-safe