Metadata-Version: 1.0
Name: pylexbuilder
Version: 0.4.0
Summary: Python AWS Lex Builder
Home-page: https://github.com/wavycloud/pylexbuilder
Author: WavyCloud
Author-email: UNKNOWN
License: MIT License
Keywords: aws python lex lambda automation
Platform: UNKNOWN
